fschat_flagembedding_worker/__init__.py
fschat_flagembedding_worker/serve/__init__.py
fschat_flagembedding_worker/serve/flagmodel_worker.py
fschat_flagembedding_worker/serve/flagreranker_worker.py
fschat_FlagEmbedding_worker-0.1.1.dist-info/LICENSE
fschat_FlagEmbedding_worker-0.1.1.dist-info/METADATA
fschat_FlagEmbedding_worker-0.1.1.dist-info/WHEEL
fschat_FlagEmbedding_worker-0.1.1.dist-info/top_level.txt
fschat_FlagEmbedding_worker-0.1.1.dist-info/RECORD
