Metadata-Version: 2.1
Name: fschat-FlagEmbedding-worker
Version: 0.1.1
Summary: FlagEmbedding model worker for fastchat.
Home-page: UNKNOWN
Author: Jiang XiaoKai
Maintainer: Jiang XiaoKai
License: MIT
Keywords: fastchat,FlagEmbedding,model_worker
Platform: UNKNOWN
Classifier: Development Status :: 5 - Production/Stable
Classifier: Intended Audience :: Developers
Classifier: Topic :: Software Development :: Libraries :: Python Modules
Classifier: License :: OSI Approved :: MIT License
Classifier: Programming Language :: Python :: 3
Classifier: Programming Language :: Python :: 3 :: Only
License-File: LICENSE
Requires-Dist: FlagEmbedding
Requires-Dist: uvicorn
Requires-Dist: torch
Requires-Dist: fschat
Requires-Dist: numpy
